OneClick/SidraTools.py
OneClick/__init__.py
OneClick-3.0.1.dist-info/LICENSE
OneClick-3.0.1.dist-info/METADATA
OneClick-3.0.1.dist-info/WHEEL
OneClick-3.0.1.dist-info/top_level.txt
OneClick-3.0.1.dist-info/RECORD
