Metadata-Version: 2.1
Name: OneClick
Version: 3.0.1
Summary: OneClik 
Home-page: https://github.com/SidraELEzz/EmailChecker
Author: SidraELEzz
Author-email: 
Project-URL: Bug Tracker, https://github.com/pypa/sampleproject/issues
Keywords: OneClick
Classifier: Development Status :: 1 - Planning
Classifier: Intended Audience :: Developers
Classifier: Programming Language :: Python :: 3
Classifier: Operating System :: Unix
Classifier: Operating System :: MacOS :: MacOS X
Classifier: Operating System :: Microsoft :: Windows
License-File: LICENSE
Requires-Dist: requests
